autotestmap/__init__.py
autotestmap/cli.py
autotestmap/core.py
autotestmap/utils.py
autotestmap-1.0.0.dist-info/licenses/LICENSE
tests/__init__.py
tests/test_core.py
autotestmap-1.0.0.dist-info/METADATA
autotestmap-1.0.0.dist-info/WHEEL
autotestmap-1.0.0.dist-info/entry_points.txt
autotestmap-1.0.0.dist-info/top_level.txt
autotestmap-1.0.0.dist-info/RECORD
